asf_hyp3/__init__.py
asf_hyp3/localizer.py
asf_hyp3/messages.json
asf_hyp3/scripts.py
asf_hyp3/scripts/__init__.py
asf_hyp3/scripts/download_products.py
asf_hyp3/scripts/load_granules.py
asf_hyp3-3.0.3.dist-info/METADATA
asf_hyp3-3.0.3.dist-info/WHEEL
asf_hyp3-3.0.3.dist-info/top_level.txt
asf_hyp3-3.0.3.dist-info/RECORD
