Metadata-Version: 2.1
Name: asf-hyp3
Version: 3.0.3
Summary: Api for ASF's hyp3 system
Home-page: https://github.com/asfadmin/hyp3-api
Author: ASF Student Development Team 2017
Author-email: eng.accts@asf.alaska.edu
License: License :: OSI Approved :: GNU General Public License v2 or later (GPLv2+)
Keywords: hyp3 api hyp3-api asf
Platform: UNKNOWN
Classifier: Development Status :: 3 - Alpha
Classifier: Intended Audience :: Science/Research
Classifier: Topic :: Scientific/Engineering :: GIS
Classifier: Programming Language :: Python :: 2.7
Classifier: Programming Language :: Python :: 3.4
Requires-Dist: requests (>=2.14.0)
Requires-Dist: pyshp (>=1.2.11)
Requires-Dist: pygeoif (>=0.7)
